{"status": "active", "preferred_support_tool": "", "preferred_support_url": "", "labels": [], "private": false, "creation_date": "2011-04-16", "socialnetworks": [], "tools": [{"sourceforge_group_id": 534017, "mount_point": "summary", "name": "summary", "label": "Summary"}, {"mount_point": "support", "name": "support", "label": "Support"}, {"mount_point": "reviews", "name": "reviews", "label": "Reviews"}, {"mount_point": "wiki", "name": "wiki", "label": "Wiki"}, {"mount_point": "files", "name": "files", "label": "Files"}, {"mount_point": "activity", "name": "activity", "label": "Activity"}], "categories": {"developmentstatus": [], "environment": [], "language": [], "license": [], "database": [], "topic": [], "audience": [], "translation": [], "os": []}, "_id": "5167036934309d5b8c7b9ab5", "name": "a-b", "url": "http://sourceforge.net/p/a-b/", "icon_url": null, "video_url": "", "screenshots": [], "summary": "", "short_description": "this is a-b,is the website.", "moved_to_url": "", "shortname": "a-b", "developers": [{"url": "http://sourceforge.net/u/timcsy/", "username": "timcsy", "name": "c sy"}], "external_homepage": "http://a-b.sourceforge.net"}

