{"status": "active", "preferred_support_tool": "_url", "preferred_support_url": "http://www.lightdesigner.com.pl/", "labels": [], "private": false, "creation_date": "2013-09-01", "socialnetworks": [{"accounturl": "", "socialnetwork": "Twitter"}], "tools": [{"mount_point": "reviews", "name": "reviews", "label": "Reviews"}, {"mount_point": "files", "name": "files", "label": "Files"}, {"mount_point": "discussion", "name": "discussion", "label": "Discussion"}, {"sourceforge_group_id": 1943912, "mount_point": "summary", "name": "summary", "label": "Summary"}, {"mount_point": "support", "name": "support", "label": "Support"}, {"mount_point": "wiki", "name": "wiki", "label": "Wiki"}, {"mount_point": "code", "name": "git", "label": "Code"}, {"mount_point": "tickets", "name": "tickets", "label": "Tickets"}], "categories": {"developmentstatus": [], "environment": [], "language": [], "license": [], "database": [], "topic": [], "audience": [], "translation": [], "os": []}, "_id": "52238feab9363c16c0c2d0be", "name": "nagłośnienie imprez warszawa", "url": "http://sourceforge.net/p/a0pr0hus91/", "icon_url": null, "video_url": "", "screenshots": [], "summary": "", "short_description": "", "moved_to_url": "", "shortname": "a0pr0hus91", "developers": [{"url": "http://sourceforge.net/u/a0pr0hus91/", "username": "a0pr0hus91", "name": "a0pr0hus91"}], "external_homepage": "http://www.lightdesigner.com.pl/"}


