{"status": "active", "preferred_support_tool": "", "preferred_support_url": "", "labels": [], "private": false, "creation_date": "2015-01-05", "socialnetworks": [{"accounturl": "", "socialnetwork": "Twitter"}, {"accounturl": null, "socialnetwork": "Facebook"}], "tools": [{"mount_point": "discussion", "name": "discussion", "label": "Discussion"}, {"mount_point": "support", "name": "support", "label": "Support"}, {"mount_point": "reviews", "name": "reviews", "label": "Reviews"}, {"mount_point": "activity", "name": "activity", "label": "Activity"}, {"mount_point": "files", "name": "files", "label": "Files"}, {"sourceforge_group_id": 2388958, "mount_point": "summary", "name": "summary", "label": "Summary"}, {"mount_point": "wiki", "name": "wiki", "label": "Wiki"}, {"mount_point": "tickets", "name": "tickets", "label": "Tickets"}, {"mount_point": "code", "name": "hg", "label": "Code"}], "categories": {"developmentstatus": [], "environment": [], "language": [], "license": [], "database": [], "topic": [], "audience": [], "translation": [], "os": []}, "_id": "54ab03c190954722ce45531f", "name": "template.js", "url": "http://sourceforge.net/p/a1soft-templatejs/", "icon_url": null, "video_url": null, "screenshots": [], "summary": "Template engine for java using javascript as template language.", "short_description": "", "moved_to_url": "", "shortname": "a1soft-templatejs", "developers": [{"url": "http://sourceforge.net/u/a1soft/", "username": "a1soft", "name": "Alexander Solodukhin"}], "external_homepage": "http://a1soft-templatejs.sourceforge.net"}

