{"status": "active", "preferred_support_tool": "", "preferred_support_url": "", "labels": [], "private": false, "creation_date": "2008-01-16", "socialnetworks": [], "tools": [{"sourceforge_group_id": 215062, "mount_point": "summary", "name": "summary", "label": "Summary"}, {"mount_point": "support", "name": "support", "label": "Support"}, {"mount_point": "reviews", "name": "reviews", "label": "Reviews"}, {"mount_point": "wiki", "name": "wiki", "label": "Wiki"}, {"mount_point": "files", "name": "files", "label": "Files"}, {"mount_point": "news", "name": "blog", "label": "News"}, {"mount_point": "discussion", "name": "discussion", "label": "Discussion"}, {"mount_point": "activity", "name": "activity", "label": "Activity"}, {"mount_point": "mailman", "name": "mailman", "label": "Mailing Lists"}], "categories": {"developmentstatus": [{"fullpath": "Development Status :: 2 - Pre-Alpha", "fullname": "2 - Pre-Alpha", "shortname": "prealpha", "id": 8}, {"fullpath": "Development Status :: 1 - Planning", "fullname": "1 - Planning", "shortname": "planning", "id": 7}], "environment": [], "language": [], "license": [{"fullpath": "License :: OSI-Approved Open Source :: BSD License", "fullname": "BSD License", "shortname": "bsd", "id": 187}], "database": [], "topic": [{"fullpath": "Topic :: Other/Nonlisted Topic", "fullname": "Other/Nonlisted Topic", "shortname": "other", "id": 234}, {"fullpath": "Topic :: Religion and Philosophy", "fullname": "Religion and Philosophy", "shortname": "religion", "id": 132}], "audience": [{"fullpath": "Intended Audience :: by End-User Class :: Developers", "fullname": "Developers", "shortname": "developers", "id": 3}, {"fullpath": "Intended Audience :: by End-User Class :: End Users/Desktop", "fullname": "End Users/Desktop", "shortname": "endusers", "id": 2}], "translation": [], "os": [{"fullpath": "Operating System :: Modern (Vendor-Supported) Desktop Operating Systems :: Win2K", "fullname": "Win2K", "shortname": "mswin_2000", "id": 420}, {"fullpath": "Operating System :: Modern (Vendor-Supported) Desktop Operating Systems :: Linux", "fullname": "Linux", "shortname": "linux", "id": 201}, {"fullpath": "Operating System :: Modern (Vendor-Supported) Desktop Operating Systems :: NetBSD", "fullname": "NetBSD", "shortname": "netbsd", "id": 204}, {"fullpath": "Operating System :: Modern (Vendor-Supported) Desktop Operating Systems :: OS X", "fullname": "OS X", "shortname": "macosx", "id": 309}, {"fullpath": "Operating System :: Modern (Vendor-Supported) Desktop Operating Systems :: WinXP", "fullname": "WinXP", "shortname": "mswin_xp", "id": 419}]}, "_id": "514cc676271846033bf6dfa6", "name": "Angel Accountability Monitor", "url": "http://sourceforge.net/p/aaccountmon/", "icon_url": null, "video_url": "", "screenshots": [], "summary": "", "short_description": "An attempt to create an open source, freely available Internet accountability program. Designed to provide a free (libre and gratis) and improved version of the X3Watch program.", "moved_to_url": "", "shortname": "aaccountmon", "developers": [{"url": "http://sourceforge.net/u/cridiron/", "username": "cridiron", "name": "Max M."}], "external_homepage": "http://aaccountmon.sourceforge.net"}

