{"status": "active", "preferred_support_tool": "", "preferred_support_url": "", "labels": [], "private": false, "creation_date": "2009-11-15", "socialnetworks": [], "tools": [{"sourceforge_group_id": 288369, "mount_point": "summary", "name": "summary", "label": "Summary"}, {"mount_point": "support", "name": "support", "label": "Support"}, {"mount_point": "reviews", "name": "reviews", "label": "Reviews"}, {"mount_point": "wiki", "name": "wiki", "label": "Wiki"}, {"mount_point": "files", "name": "files", "label": "Files"}, {"mount_point": "code", "name": "svn", "label": "Code"}], "categories": {"developmentstatus": [], "environment": [], "language": [], "license": [], "database": [], "topic": [], "audience": [], "translation": [], "os": []}, "_id": "5165b468e88f3d0a9d338f77", "name": "aain", "url": "http://sourceforge.net/p/aain/", "icon_url": null, "video_url": "", "screenshots": [], "summary": "", "short_description": "Probnai versia cozdania xranilisha", "moved_to_url": "", "shortname": "aain", "developers": [{"url": "http://sourceforge.net/u/pyler/", "username": "pyler", "name": "ddd sss"}], "external_homepage": "http://aain.sourceforge.net"}

