{"status": "active", "preferred_support_tool": "", "preferred_support_url": "", "labels": [], "private": false, "creation_date": "2001-10-24", "socialnetworks": [], "tools": [{"sourceforge_group_id": 38508, "mount_point": "summary", "name": "summary", "label": "Summary"}, {"mount_point": "support", "name": "support", "label": "Support"}, {"mount_point": "reviews", "name": "reviews", "label": "Reviews"}, {"mount_point": "wiki", "name": "wiki", "label": "Wiki"}, {"mount_point": "files", "name": "files", "label": "Files"}, {"mount_point": "mailman", "name": "mailman", "label": "Mailing Lists"}, {"mount_point": "bugs", "name": "tickets", "label": "Bugs"}, {"mount_point": "activity", "name": "activity", "label": "Activity"}], "categories": {"developmentstatus": [{"fullpath": "Development Status :: 6 - Mature", "fullname": "6 - Mature", "shortname": "mature", "id": 12}, {"fullpath": "Development Status :: 5 - Production/Stable", "fullname": "5 - Production/Stable", "shortname": "production", "id": 11}], "environment": [{"fullpath": "User Interface :: Web-based", "fullname": "Web-based", "shortname": "web", "id": 237}, {"fullpath": "User Interface :: Non-interactive (Daemon)", "fullname": "Non-interactive (Daemon)", "shortname": "daemon", "id": 238}], "language": [{"fullpath": "Programming Language :: C", "fullname": "C", "shortname": "c", "id": 164}], "license": [{"fullpath": "License :: OSI-Approved Open Source :: Apache Software License", "fullname": "Apache Software License", "shortname": "apache", "id": 296}], "database": [], "topic": [{"fullpath": "Topic :: Internet :: WWW/HTTP :: HTTP Servers", "fullname": "HTTP Servers", "shortname": "httpservers", "id": 250}], "audience": [{"fullpath": "Intended Audience :: by End-User Class :: System Administrators", "fullname": "System Administrators", "shortname": "sysadmins", "id": 4}, {"fullpath": "Intended Audience :: by End-User Class :: Developers", "fullname": "Developers", "shortname": "developers", "id": 3}, {"fullpath": "Intended Audience :: by End-User Class :: End Users/Desktop", "fullname": "End Users/Desktop", "shortname": "endusers", "id": 2}], "translation": [], "os": [{"fullpath": "Operating System :: Modern (Vendor-Supported) Desktop Operating Systems :: Linux", "fullname": "Linux", "shortname": "linux", "id": 201}, {"fullpath": "Operating System :: Other Operating Systems :: SGI IRIX", "fullname": "SGI IRIX", "shortname": "irix", "id": 211}, {"fullpath": "Operating System :: Grouping and Descriptive Categories :: OS Independent (Written in an interpreted language)", "fullname": "OS Independent (Written in an interpreted language)", "shortname": "independent", "id": 235}, {"fullpath": "Operating System :: Grouping and Descriptive Categories :: All POSIX (Linux/BSD/UNIX-like OSes)", "fullname": "All POSIX (Linux/BSD/UNIX-like OSes)", "shortname": "posix", "id": 200}]}, "_id": "513a1633e88f3d0ab975ab82", "name": "Accelerating Apache Project", "url": "http://sourceforge.net/p/aap/", "icon_url": null, "video_url": "", "screenshots": [], "summary": "", "short_description": "The Accelerating Apache Project was SGI's effort to increase the performance of the Apache HTTP server.  It has a new home now on SourceForge, courtesy of SGI.  Now it seeks a new owner and a fresh start.  Want to help make Apache MORE than 10x faster?", "moved_to_url": "", "shortname": "aap", "developers": [{"url": "http://sourceforge.net/u/mabbott/", "username": "mabbott", "name": "Mike Abbott"}], "external_homepage": "http://aap.sourceforge.net"}

