{"status": "active", "preferred_support_tool": "", "preferred_support_url": "", "labels": [], "private": false, "creation_date": "2010-08-16", "socialnetworks": [], "tools": [{"sourceforge_group_id": 343435, "mount_point": "summary", "name": "summary", "label": "Summary"}, {"mount_point": "support", "name": "support", "label": "Support"}, {"mount_point": "reviews", "name": "reviews", "label": "Reviews"}, {"mount_point": "wiki", "name": "wiki", "label": "Wiki"}, {"mount_point": "files", "name": "files", "label": "Files"}, {"mount_point": "code", "name": "git", "label": "Code"}], "categories": {"developmentstatus": [], "environment": [], "language": [], "license": [], "database": [], "topic": [], "audience": [], "translation": [], "os": []}, "_id": "5165b1f2e88f3d35dcf698ae", "name": "gPhone-based Activity Recommendation", "url": "http://sourceforge.net/p/aar/", "icon_url": null, "video_url": "", "screenshots": [], "summary": "", "short_description": "This is a private project.", "moved_to_url": "", "shortname": "aar", "developers": [{"url": "http://sourceforge.net/u/ustfyp2010/", "username": "ustfyp2010", "name": "UST FYP 2010"}], "external_homepage": "http://aar.sourceforge.net"}

