{"status": "active", "preferred_support_tool": "_url", "preferred_support_url": "http://sourceforge.net/project/memberlist.php?group_id=272321", "labels": [], "private": false, "creation_date": "2009-08-05", "socialnetworks": [], "tools": [{"sourceforge_group_id": 272321, "mount_point": "summary", "name": "summary", "label": "Summary"}, {"mount_point": "support", "name": "support", "label": "Support"}, {"mount_point": "reviews", "name": "reviews", "label": "Reviews"}, {"mount_point": "files", "name": "files", "label": "Files"}, {"mount_point": "wiki", "name": "wiki", "label": "Wiki"}, {"mount_point": "bugs", "name": "tickets", "label": "Bugs"}, {"mount_point": "feature-requests", "name": "tickets", "label": "Feature Requests"}, {"mount_point": "discussion", "name": "discussion", "label": "Discussion"}, {"mount_point": "code", "name": "svn", "label": "Code"}, {"mount_point": "activity", "name": "activity", "label": "Activity"}], "categories": {"developmentstatus": [{"fullpath": "Development Status :: 5 - Production/Stable", "fullname": "5 - Production/Stable", "shortname": "production", "id": 11}], "environment": [{"fullpath": "User Interface :: Web-based", "fullname": "Web-based", "shortname": "web", "id": 237}], "language": [{"fullpath": "Programming Language :: PHP", "fullname": "PHP", "shortname": "php", "id": 183}, {"fullpath": "Programming Language :: JavaScript", "fullname": "JavaScript", "shortname": "JavaScript", "id": 280}], "license": [{"fullpath": "License :: OSI-Approved Open Source :: GNU General Public License version 2.0 (GPLv2)", "fullname": "GNU General Public License version 2.0 (GPLv2)", "shortname": "gpl", "id": 15}], "database": [{"fullpath": "Database Environment :: Network-based DBMS :: MySQL", "fullname": "MySQL", "shortname": "db_net_mysql", "id": 524}, {"fullpath": "Database Environment :: Network-based DBMS :: SQLite", "fullname": "SQLite", "shortname": "db_net_sqlite", "id": 531}, {"fullpath": "Database Environment :: Database API :: SQL-based", "fullname": "SQL-based", "shortname": "db_api_sql", "id": 508}], "topic": [{"fullpath": "Topic :: Internet :: WWW/HTTP :: Site Management", "fullname": "Site Management", "shortname": "sitemanagement", "id": 243}, {"fullpath": "Topic :: Internet :: WWW/HTTP :: Dynamic Content :: CMS Systems", "fullname": "CMS Systems", "shortname": "cms", "id": 644}], "audience": [{"fullpath": "Intended Audience :: by End-User Class :: Advanced End Users", "fullname": "Advanced End Users", "shortname": "enduser_advanced", "id": 536}, {"fullpath": "Intended Audience :: by End-User Class :: Developers", "fullname": "Developers", "shortname": "developers", "id": 3}, {"fullpath": "Intended Audience :: by End-User Class :: End Users/Desktop", "fullname": "End Users/Desktop", "shortname": "endusers", "id": 2}], "translation": [{"fullpath": "Translations :: English", "fullname": "English", "shortname": "english", "id": 275}], "os": [{"fullpath": "Operating System :: Grouping and Descriptive Categories :: OS Portable (Source code to work with many OS platforms)", "fullname": "OS Portable (Source code to work with many OS platforms)", "shortname": "os_portable", "id": 436}]}, "_id": "516efe272718467b8b82e6c3", "name": "Aardvertiser", "url": "http://sourceforge.net/p/aardvertiser/", "icon_url": "http://sourceforge.net/p/aardvertiser/icon", "video_url": "", "screenshots": [], "summary": "", "short_description": "A Joomla 1.5 component for advertising items in a 'classified ads' style on a Joomla site complete with extra modules and plugins for improved functionality.", "moved_to_url": "", "shortname": "aardvertiser", "developers": [{"url": "http://sourceforge.net/u/simonp22/", "username": "simonp22", "name": "Simon Phillips"}, {"url": "http://sourceforge.net/u/userid-2135078/", "username": "tim_redman", "name": "Tim Redman"}], "external_homepage": "http://aardvertiser.sourceforge.net"}

