{"status": "active", "preferred_support_tool": "", "preferred_support_url": "", "labels": [], "private": false, "creation_date": "2008-04-05", "socialnetworks": [], "tools": [{"mount_point": "activity", "name": "activity", "label": "Activity"}, {"sourceforge_group_id": 223834, "mount_point": "summary", "name": "summary", "label": "Summary"}, {"mount_point": "support", "name": "support", "label": "Support"}, {"mount_point": "reviews", "name": "reviews", "label": "Reviews"}, {"mount_point": "wiki", "name": "wiki", "label": "Wiki"}, {"mount_point": "files", "name": "files", "label": "Files"}, {"mount_point": "news", "name": "blog", "label": "News"}, {"mount_point": "code", "name": "svn", "label": "Code"}, {"mount_point": "mailman", "name": "mailman", "label": "Mailing Lists"}], "categories": {"developmentstatus": [{"fullpath": "Development Status :: 1 - Planning", "fullname": "1 - Planning", "shortname": "planning", "id": 7}], "environment": [{"fullpath": "User Interface :: Grouping and Descriptive Categories (UI) :: Project is a 3D engine", "fullname": "Project is a 3D engine", "shortname": "ui_meta_3d", "id": 466}, {"fullpath": "User Interface :: Toolkits/Libraries :: DirectX", "fullname": "DirectX", "shortname": "ui_directx", "id": 485}], "language": [{"fullpath": "Programming Language :: C#", "fullname": "C#", "shortname": "csharp", "id": 271}], "license": [{"fullpath": "License :: OSI-Approved Open Source :: MIT License", "fullname": "MIT License", "shortname": "mit", "id": 188}], "database": [], "topic": [{"fullpath": "Topic :: Games/Entertainment :: Role-Playing", "fullname": "Role-Playing", "shortname": "rpg", "id": 84}], "audience": [{"fullpath": "Intended Audience :: by End-User Class :: Developers", "fullname": "Developers", "shortname": "developers", "id": 3}], "translation": [{"fullpath": "Translations :: English", "fullname": "English", "shortname": "english", "id": 275}], "os": [{"fullpath": "Operating System :: Modern (Vendor-Supported) Desktop Operating Systems :: WinXP", "fullname": "WinXP", "shortname": "mswin_xp", "id": 419}]}, "_id": "5165b56d34309d5b8c7af6a3", "name": "AARPG", "url": "http://sourceforge.net/p/aarpg/", "icon_url": null, "video_url": "", "screenshots": [], "summary": "", "short_description": "AARPG is an engine for a Auto Adjusting Role Plaing Game The goal of this project is to create an game engine for RPG's with a minimum need of balancing and scripting. Skill levels are adjusted automatically by using or not using the skill. ", "moved_to_url": "", "shortname": "aarpg", "developers": [{"url": "http://sourceforge.net/u/osre/", "username": "osre", "name": "Reinhard Ostermeier"}], "external_homepage": "http://aarpg.sourceforge.net"}

