{"status": "active", "preferred_support_tool": "", "preferred_support_url": "", "labels": [], "private": false, "creation_date": "2010-10-15", "socialnetworks": [], "tools": [{"sourceforge_group_id": 362412, "mount_point": "summary", "name": "summary", "label": "Summary"}, {"mount_point": "support", "name": "support", "label": "Support"}, {"mount_point": "reviews", "name": "reviews", "label": "Reviews"}, {"mount_point": "files", "name": "files", "label": "Files"}, {"mount_point": "wiki", "name": "wiki", "label": "Wiki"}, {"mount_point": "code", "name": "git", "label": "Code"}, {"mount_point": "activity", "name": "activity", "label": "Activity"}], "categories": {"developmentstatus": [], "environment": [], "language": [], "license": [], "database": [], "topic": [], "audience": [], "translation": [], "os": []}, "_id": "518412f65fcbc9796049f6c0", "name": "Abbadon", "url": "http://sourceforge.net/p/abbadon-projekt/", "icon_url": null, "video_url": "", "screenshots": [], "summary": "", "short_description": "WoW Objecte, NPC's und vieles mehr.", "moved_to_url": "", "shortname": "abbadon-projekt", "developers": [{"url": "http://sourceforge.net/u/zornschatten/", "username": "zornschatten", "name": "Abbadon"}], "external_homepage": "http://zs.space-sponsor.eu/"}

