{"status": "active", "preferred_support_tool": "", "preferred_support_url": "", "labels": [], "private": false, "creation_date": "2011-09-27", "socialnetworks": [], "tools": [{"mount_point": "home", "name": "wiki", "label": "Home"}, {"mount_point": "code", "name": "svn", "label": "Code"}, {"mount_point": "abcgame", "name": "svn", "label": "ABCGame"}, {"mount_point": "files", "name": "files", "label": "Files"}, {"sourceforge_group_id": 600175, "mount_point": "summary", "name": "summary", "label": "Summary"}, {"mount_point": "reviews", "name": "reviews", "label": "Reviews"}, {"mount_point": "support", "name": "support", "label": "Support"}, {"mount_point": "activity", "name": "activity", "label": "Activity"}], "categories": {"developmentstatus": [], "environment": [], "language": [], "license": [], "database": [], "topic": [], "audience": [], "translation": [], "os": []}, "_id": "4e818c490594ca336800065a", "name": "ABCGame", "url": "http://sourceforge.net/p/abcgame/", "icon_url": null, "video_url": "", "screenshots": [], "summary": "", "short_description": "", "moved_to_url": "", "shortname": "abcgame", "developers": [{"url": "http://sourceforge.net/u/maheshbabu159/", "username": "maheshbabu159", "name": "maheshbabu159"}], "external_homepage": ""}

