{"status": "active", "preferred_support_tool": "", "preferred_support_url": "", "labels": [], "private": false, "creation_date": "2008-02-12", "socialnetworks": [], "tools": [{"mount_point": "files", "name": "files", "label": "Files"}, {"sourceforge_group_id": 217680, "mount_point": "summary", "name": "summary", "label": "Summary"}, {"mount_point": "support", "name": "support", "label": "Support"}, {"mount_point": "reviews", "name": "reviews", "label": "Reviews"}, {"mount_point": "wiki", "name": "wiki", "label": "Wiki"}, {"mount_point": "activity", "name": "activity", "label": "Activity"}, {"mount_point": "mailman", "name": "mailman", "label": "Mailing Lists"}], "categories": {"developmentstatus": [{"fullpath": "Development Status :: 4 - Beta", "fullname": "4 - Beta", "shortname": "beta", "id": 10}], "environment": [{"fullpath": "User Interface :: Graphical :: Win32 (MS Windows)", "fullname": "Win32 (MS Windows)", "shortname": "win32", "id": 230}, {"fullpath": "User Interface :: Non-interactive (Daemon)", "fullname": "Non-interactive (Daemon)", "shortname": "daemon", "id": 238}], "language": [], "license": [{"fullpath": "License :: OSI-Approved Open Source :: GNU General Public License version 2.0 (GPLv2)", "fullname": "GNU General Public License version 2.0 (GPLv2)", "shortname": "gpl", "id": 15}], "database": [], "topic": [{"fullpath": "Topic :: Communications", "fullname": "Communications", "shortname": "communications", "id": 20}, {"fullpath": "Topic :: Software Development :: User Interfaces", "fullname": "User Interfaces", "shortname": "softwaredev_ui", "id": 561}], "audience": [{"fullpath": "Intended Audience :: by End-User Class :: Developers", "fullname": "Developers", "shortname": "developers", "id": 3}, {"fullpath": "Intended Audience :: by End-User Class :: End Users/Desktop", "fullname": "End Users/Desktop", "shortname": "endusers", "id": 2}], "translation": [], "os": [{"fullpath": "Operating System :: Grouping and Descriptive Categories :: 32-bit MS Windows (NT/2000/XP)", "fullname": "32-bit MS Windows (NT/2000/XP)", "shortname": "winnt", "id": 219}]}, "_id": "5159dd0027184634a2a27610", "name": "Allen Bradley SLC 5/05 Ethernet Driver", "url": "http://sourceforge.net/p/abethernet/", "icon_url": null, "video_url": "", "screenshots": [{"url": "http://sourceforge.net/p/abethernet/screenshot/159718.jpg", "caption": "Allen Bradley Utilities Written using AB Ethernet Control", "thumbnail_url": "http://sourceforge.net/p/abethernet/screenshot/159718.jpg/thumb"}], "summary": "", "short_description": "Utilities for reading/writing data in a SLC 5/05 over ethernet. The driver uses the CSP protocol, sometimes refered to as AB/Ethernet. Written in Visual Basic 2008. Works in free express version. Can be used to build a free HMI. NOTE: This is NOT Etherne", "moved_to_url": "", "shortname": "abethernet", "developers": [{"url": "http://sourceforge.net/u/arj3090/", "username": "arj3090", "name": "Archie"}], "external_homepage": "http://abethernet.sourceforge.net"}

