{"status": "active", "preferred_support_tool": "", "preferred_support_url": "", "labels": [], "private": false, "creation_date": "2012-03-18", "socialnetworks": [], "tools": [{"mount_point": "wiki", "name": "wiki", "label": "Wiki"}, {"mount_point": "downloads", "name": "files", "label": "Files"}, {"mount_point": "code", "name": "git", "label": "Code"}, {"mount_point": "discussion", "name": "discussion", "label": "Discussion"}, {"mount_point": "tickets", "name": "tickets", "label": "Tickets"}, {"sourceforge_group_id": 725747, "mount_point": "summary", "name": "summary", "label": "Summary"}, {"mount_point": "reviews", "name": "reviews", "label": "Reviews"}, {"mount_point": "support", "name": "support", "label": "Support"}, {"mount_point": "activity", "name": "activity", "label": "Activity"}], "categories": {"developmentstatus": [], "environment": [], "language": [], "license": [], "database": [], "topic": [], "audience": [], "translation": [], "os": []}, "_id": "4f662dbf0594ca2c370006ac", "name": "ablah", "url": "http://sourceforge.net/p/ablah/", "icon_url": null, "video_url": "", "screenshots": [], "summary": "asdasdasd", "short_description": "asdasdas", "moved_to_url": "", "shortname": "ablah", "developers": [{"url": "http://sourceforge.net/u/alimjan/", "username": "alimjan", "name": "alimjan"}], "external_homepage": "a"}

