{"status": "active", "preferred_support_tool": "", "preferred_support_url": "", "labels": [], "private": false, "creation_date": "2009-10-09", "socialnetworks": [], "tools": [{"mount_point": "files", "name": "files", "label": "Files"}, {"sourceforge_group_id": 282324, "mount_point": "summary", "name": "summary", "label": "Summary"}, {"mount_point": "support", "name": "support", "label": "Support"}, {"mount_point": "reviews", "name": "reviews", "label": "Reviews"}, {"mount_point": "wiki", "name": "wiki", "label": "Wiki"}, {"mount_point": "activity", "name": "activity", "label": "Activity"}], "categories": {"developmentstatus": [{"fullpath": "Development Status :: 3 - Alpha", "fullname": "3 - Alpha", "shortname": "alpha", "id": 9}], "environment": [{"fullpath": "User Interface :: Graphical :: Gnome", "fullname": "Gnome", "shortname": "gnome", "id": 231}], "language": [{"fullpath": "Programming Language :: C", "fullname": "C", "shortname": "c", "id": 164}], "license": [{"fullpath": "License :: OSI-Approved Open Source :: Common Public Attribution License 1.0 (CPAL)", "fullname": "Common Public Attribution License 1.0 (CPAL)", "shortname": "cpal", "id": 639}, {"fullpath": "License :: OSI-Approved Open Source :: GNU Library or Lesser General Public License version 3.0 (LGPLv3)", "fullname": "GNU Library or Lesser General Public License version 3.0 (LGPLv3)", "shortname": "lgplv3", "id": 680}], "database": [], "topic": [{"fullpath": "Topic :: Desktop Environment :: Gnome", "fullname": "Gnome", "shortname": "gnome", "id": 58}], "audience": [{"fullpath": "Intended Audience :: by End-User Class :: End Users/Desktop", "fullname": "End Users/Desktop", "shortname": "endusers", "id": 2}], "translation": [], "os": [{"fullpath": "Operating System :: Modern (Vendor-Supported) Desktop Operating Systems :: Linux", "fullname": "Linux", "shortname": "linux", "id": 201}]}, "_id": "5159dccd5fcbc93da0494327", "name": "About This Mac for Linux", "url": "http://sourceforge.net/p/abouthismac4lin/", "icon_url": null, "video_url": "", "screenshots": [], "summary": "", "short_description": "Something missing from your Mac OS X lookalike? Maybe this is what you are looking for!", "moved_to_url": "", "shortname": "abouthismac4lin", "developers": [{"url": "http://sourceforge.net/u/nintendofan345/", "username": "nintendofan345", "name": "Austin Jones"}], "external_homepage": "http://abouthismac4lin.sourceforge.net"}

