{"status": "active", "preferred_support_tool": "", "preferred_support_url": "", "labels": [], "private": false, "creation_date": "2002-06-30", "socialnetworks": [], "tools": [{"sourceforge_group_id": 56808, "mount_point": "summary", "name": "summary", "label": "Summary"}, {"mount_point": "support", "name": "support", "label": "Support"}, {"mount_point": "reviews", "name": "reviews", "label": "Reviews"}, {"mount_point": "files", "name": "files", "label": "Files"}, {"mount_point": "wiki", "name": "wiki", "label": "Wiki"}, {"mount_point": "mailman", "name": "mailman", "label": "Mailing Lists"}], "categories": {"developmentstatus": [{"fullpath": "Development Status :: 2 - Pre-Alpha", "fullname": "2 - Pre-Alpha", "shortname": "prealpha", "id": 8}], "environment": [], "language": [{"fullpath": "Programming Language :: Unix Shell", "fullname": "Unix Shell", "shortname": "shell", "id": 185}], "license": [{"fullpath": "License :: OSI-Approved Open Source :: GNU General Public License version 2.0 (GPLv2)", "fullname": "GNU General Public License version 2.0 (GPLv2)", "shortname": "gpl", "id": 15}], "database": [], "topic": [{"fullpath": "Topic :: Security", "fullname": "Security", "shortname": "security", "id": 43}, {"fullpath": "Topic :: System :: Systems Administration", "fullname": "Systems Administration", "shortname": "sysadministration", "id": 253}, {"fullpath": "Topic :: System :: Logging", "fullname": "Logging", "shortname": "logging", "id": 148}], "audience": [{"fullpath": "Intended Audience :: by End-User Class :: System Administrators", "fullname": "System Administrators", "shortname": "sysadmins", "id": 4}], "translation": [{"fullpath": "Translations :: English", "fullname": "English", "shortname": "english", "id": 275}], "os": [{"fullpath": "Operating System :: Modern (Vendor-Supported) Desktop Operating Systems :: Linux", "fullname": "Linux", "shortname": "linux", "id": 201}, {"fullpath": "Operating System :: Other Operating Systems :: Other", "fullname": "Other", "shortname": "other", "id": 212}, {"fullpath": "Operating System :: Other Operating Systems :: GNU Hurd", "fullname": "GNU Hurd", "shortname": "gnuhurd", "id": 240}, {"fullpath": "Operating System :: Grouping and Descriptive Categories :: All POSIX (Linux/BSD/UNIX-like OSes)", "fullname": "All POSIX (Linux/BSD/UNIX-like OSes)", "shortname": "posix", "id": 200}, {"fullpath": "Operating System :: Grouping and Descriptive Categories :: All BSD Platforms (FreeBSD/NetBSD/OpenBSD/Apple Mac OS X)", "fullname": "All BSD Platforms (FreeBSD/NetBSD/OpenBSD/Apple Mac OS X)", "shortname": "bsd", "id": 202}]}, "_id": "5127a6fd34309d013e33620d", "name": "ACAD", "url": "http://sourceforge.net/p/acad/", "icon_url": null, "video_url": "", "screenshots": [], "summary": "", "short_description": "Automated Computer Auditing Daemon - Keep a track of what's going on with your systems: suid, sgid, world writable, hidden and unowned files monitoring as well as important file's md5sums management audits sent to your mailbox on a regular basis.", "moved_to_url": "", "shortname": "acad", "developers": [{"url": "http://sourceforge.net/u/stormvault/", "username": "stormvault", "name": "Nicolas Couture"}, {"url": "http://sourceforge.net/u/elchango/", "username": "elchango", "name": "Leandro Chango"}], "external_homepage": "http://sourceforge.net/projects/acad/"}
