{"status": "active", "preferred_support_tool": "tickets", "preferred_support_url": "", "labels": [], "private": false, "creation_date": "2013-10-30", "socialnetworks": [{"accounturl": "", "socialnetwork": "Twitter"}], "tools": [{"mount_point": "files", "name": "files", "label": "Files"}, {"mount_point": "support", "name": "support", "label": "Support"}, {"mount_point": "reviews", "name": "reviews", "label": "Reviews"}, {"sourceforge_group_id": 1994648, "mount_point": "summary", "name": "summary", "label": "Summary"}, {"mount_point": "wiki", "name": "wiki", "label": "Wiki"}, {"mount_point": "tickets", "name": "tickets", "label": "Tickets"}], "categories": {"developmentstatus": [], "environment": [], "language": [], "license": [], "database": [], "topic": [], "audience": [], "translation": [], "os": []}, "_id": "5271455ba02bb14789e0a2be", "name": "aCalculator - Calculator", "url": "http://sourceforge.net/p/acalculator-calculator/", "icon_url": null, "video_url": "", "screenshots": [], "summary": "", "short_description": "", "moved_to_url": "", "shortname": "acalculator-calculator", "developers": [{"url": "http://sourceforge.net/u/beatmod/", "username": "beatmod", "name": "Lukas Trimmel"}], "external_homepage": null}
