{"status": "active", "preferred_support_tool": "wiki", "preferred_support_url": "", "labels": [], "private": false, "creation_date": "2011-11-16", "socialnetworks": [], "tools": [{"mount_point": "home", "name": "wiki", "label": "Home"}, {"mount_point": "downloads", "name": "files", "label": "Files"}, {"mount_point": "wiki", "name": "wiki", "label": "Wiki"}, {"mount_point": "blog", "name": "blog", "label": "Blog"}, {"mount_point": "discussion", "name": "discussion", "label": "Discussion"}, {"mount_point": "code", "name": "git", "label": "Code"}, {"mount_point": "tickets", "name": "tickets", "label": "Tickets"}, {"sourceforge_group_id": 629824, "mount_point": "summary", "name": "summary", "label": "Summary"}, {"mount_point": "reviews", "name": "reviews", "label": "Reviews"}, {"mount_point": "support", "name": "support", "label": "Support"}, {"mount_point": "activity", "name": "activity", "label": "Activity"}], "categories": {"developmentstatus": [], "environment": [], "language": [], "license": [], "database": [], "topic": [], "audience": [], "translation": [], "os": []}, "_id": "4ec410b31be1ce10f200043c", "name": "ACBlogObject", "url": "http://sourceforge.net/p/acblogobject/", "icon_url": null, "video_url": "", "screenshots": [{"url": "http://sourceforge.net/p/acblogobject/screenshot/blogExample.jpg", "caption": "Basic blog example", "thumbnail_url": "http://sourceforge.net/p/acblogobject/screenshot/blogExample.jpg/thumb"}], "summary": "Javascript object implemention of a blog", "short_description": "ACBlog  is a set of  javascript files  that provide the ability to include basic blogging functionality to a web page.  By passing a configuration object at creation time, the application using ACBlog can customize the blog. It supports\r\n\r\nTo use the object, the calling application must first run a php script that builds the Javascript object that is downloaded. The application Javascript must then create an ACBlogObject instance passing it a configuration file. Then the application uses an API call to create an individual blogs.\r\n\r\nOriginally created at Amherst College as part of project to create an advanced map marker option for Google Maps (soon to be its own open source project called ACMapInterfaceObject), the blog object has been spun-off as a community-developed open source project under the MIT/X license. ", "moved_to_url": "", "shortname": "acblogobject", "developers": [{"url": "http://sourceforge.net/u/pdchapin/", "username": "pdchapin", "name": "Paul Chapin"}], "external_homepage": ""}
