{"status": "active", "preferred_support_tool": "", "preferred_support_url": "", "labels": [], "private": false, "creation_date": "2002-02-10", "socialnetworks": [], "tools": [{"sourceforge_group_id": 46380, "mount_point": "summary", "name": "summary", "label": "Summary"}, {"mount_point": "support", "name": "support", "label": "Support"}, {"mount_point": "reviews", "name": "reviews", "label": "Reviews"}, {"mount_point": "files", "name": "files", "label": "Files"}, {"mount_point": "wiki", "name": "wiki", "label": "Wiki"}, {"mount_point": "mailman", "name": "mailman", "label": "Mailing Lists"}, {"mount_point": "activity", "name": "activity", "label": "Activity"}], "categories": {"developmentstatus": [], "environment": [], "language": [], "license": [], "database": [], "topic": [], "audience": [], "translation": [], "os": []}, "_id": "5127a6fd271846233225ac39", "name": "accessible website toolkit", "url": "http://sourceforge.net/p/accesstools/", "icon_url": null, "video_url": "", "screenshots": [], "summary": "", "short_description": "This software will help webmasters easily create sites that are accessible to everyone on the internet. Future plans are to include php, mysql, and web server software along with the core php files.", "moved_to_url": "", "shortname": "accesstools", "developers": [{"url": "http://sourceforge.net/u/alex8887/", "username": "alex8887", "name": "Alex8887"}], "external_homepage": "http://accesstools.sourceforge.net"}
