{"status": "active", "preferred_support_tool": "", "preferred_support_url": "", "labels": [], "private": false, "creation_date": "2006-12-15", "socialnetworks": [], "tools": [{"sourceforge_group_id": 184979, "mount_point": "summary", "name": "summary", "label": "Summary"}, {"mount_point": "support", "name": "support", "label": "Support"}, {"mount_point": "reviews", "name": "reviews", "label": "Reviews"}, {"mount_point": "wiki", "name": "wiki", "label": "Wiki"}, {"mount_point": "files", "name": "files", "label": "Files"}, {"mount_point": "mailman", "name": "mailman", "label": "Mailing Lists"}, {"mount_point": "news", "name": "blog", "label": "News"}, {"mount_point": "code", "name": "cvs", "label": "Code"}, {"mount_point": "activity", "name": "activity", "label": "Activity"}], "categories": {"developmentstatus": [{"fullpath": "Development Status :: 1 - Planning", "fullname": "1 - Planning", "shortname": "planning", "id": 7}], "environment": [{"fullpath": "User Interface :: Graphical :: Java Swing", "fullname": "Java Swing", "shortname": "ui_swing", "id": 471}], "language": [{"fullpath": "Programming Language :: Java", "fullname": "Java", "shortname": "java", "id": 198}], "license": [{"fullpath": "License :: OSI-Approved Open Source :: GNU General Public License version 2.0 (GPLv2)", "fullname": "GNU General Public License version 2.0 (GPLv2)", "shortname": "gpl", "id": 15}], "database": [], "topic": [{"fullpath": "Topic :: Scientific/Engineering :: Simulations", "fullname": "Simulations", "shortname": "simulations", "id": 600}, {"fullpath": "Topic :: Scientific/Engineering :: Mathematics", "fullname": "Mathematics", "shortname": "mathematics", "id": 98}, {"fullpath": "Topic :: Education", "fullname": "Education", "shortname": "education", "id": 71}], "audience": [{"fullpath": "Intended Audience :: by Industry or Sector :: Science/Research", "fullname": "Science/Research", "shortname": "scienceresearch", "id": 367}, {"fullpath": "Intended Audience :: by Industry or Sector :: Education", "fullname": "Education", "shortname": "education", "id": 360}], "translation": [{"fullpath": "Translations :: German", "fullname": "German", "shortname": "german", "id": 279}], "os": [{"fullpath": "Operating System :: Grouping and Descriptive Categories :: OS Independent (Written in an interpreted language)", "fullname": "OS Independent (Written in an interpreted language)", "shortname": "independent", "id": 235}]}, "_id": "513a13d734309d2f21e6b706", "name": "Approximate Counting of Graph Colorings", "url": "http://sourceforge.net/p/acgc/", "icon_url": null, "video_url": "", "screenshots": [{"url": "http://sourceforge.net/p/acgc/screenshot/111068.jpg", "caption": "Running the algorithms using the GUI.", "thumbnail_url": "http://sourceforge.net/p/acgc/screenshot/111068.jpg/thumb"}], "summary": "", "short_description": "Algorithms to estimate the number of k-colorings of a low-degree graph using samplings from a markov chain are provided.", "moved_to_url": "", "shortname": "acgc", "developers": [{"url": "http://sourceforge.net/u/tobikley/", "username": "tobikley", "name": "Tobias Kley"}], "external_homepage": "http://acgc.sourceforge.net"}
