{"status": "active", "preferred_support_tool": "", "preferred_support_url": "", "labels": [], "private": false, "creation_date": "2014-02-19", "socialnetworks": [{"accounturl": "", "socialnetwork": "Twitter"}, {"accounturl": null, "socialnetwork": "Facebook"}], "tools": [{"mount_point": "activity", "name": "activity", "label": "Activity"}, {"mount_point": "files", "name": "files", "label": "Files"}, {"sourceforge_group_id": 2105593, "mount_point": "summary", "name": "summary", "label": "Summary"}, {"mount_point": "reviews", "name": "reviews", "label": "Reviews"}, {"mount_point": "support", "name": "support", "label": "Support"}, {"mount_point": "wiki", "name": "wiki", "label": "Wiki"}, {"mount_point": "code", "name": "git", "label": "Code"}, {"mount_point": "tickets", "name": "tickets", "label": "Tickets"}, {"mount_point": "discussion", "name": "discussion", "label": "Discussion"}, {"mount_point": "blog", "name": "blog", "label": "Blog"}], "categories": {"developmentstatus": [], "environment": [], "language": [], "license": [], "database": [], "topic": [], "audience": [], "translation": [], "os": []}, "_id": "5304528da02bb11e7fa62ef5", "name": "Wa@ ac milan vs atletico madrid live ste", "url": "http://sourceforge.net/p/acmilanvsatleticomadridliveste/", "icon_url": null, "video_url": null, "screenshots": [], "summary": "", "short_description": "ac milan vs atletico madrid live stream Milan has struggled in the Serie A with only eight wins, eight draws and eight losses in 24 Italian league games this year. The team’s poor form will likely leave it out of the tournament next season despite possessing such talent as Mario Balotelli and Kaka\r\n\r\nac milan vs atletico madrid live stream\r\nCOMPETITOR :   ..\r\n\r\nUEFA Champions League\r\nDATE : feb 19  2014\r\nTIME19;45 GMT\r\n\r\nCLICK HERE===\u003C>>\u003C> http://www.fcscores.com/\r\n\r\nCLICK HERE===\u003C>>\u003C> http://www.fcscores.com/\r\n\r\nCLICK HERE===\u003C>>\u003C> http://www.fcscores.com/\r\n\r\nac milan vs atletico madrid live streamyear’s round of 16; that win foreshadowed the Spanish side’s eventual demise in the tournament.\r\n\r\n", "moved_to_url": "", "shortname": "acmilanvsatleticomadridliveste", "developers": [{"url": "http://sourceforge.net/u/zeshanawan0/", "username": "zeshanawan0", "name": "zeshan"}], "external_homepage": null}
