{"status": "active", "preferred_support_tool": "", "preferred_support_url": "", "labels": [], "private": false, "creation_date": "2014-01-24", "socialnetworks": [{"accounturl": "", "socialnetwork": "Twitter"}, {"accounturl": null, "socialnetwork": "Facebook"}], "tools": [{"mount_point": "files", "name": "files", "label": "Files"}, {"sourceforge_group_id": 2083700, "mount_point": "summary", "name": "summary", "label": "Summary"}, {"mount_point": "reviews", "name": "reviews", "label": "Reviews"}, {"mount_point": "support", "name": "support", "label": "Support"}, {"mount_point": "wiki", "name": "wiki", "label": "Wiki"}, {"mount_point": "code", "name": "svn", "label": "Code"}, {"mount_point": "activity", "name": "activity", "label": "Activity"}], "categories": {"developmentstatus": [], "environment": [], "language": [], "license": [], "database": [], "topic": [], "audience": [], "translation": [], "os": []}, "_id": "52e2d444ea406b0a20129b17", "name": "A colorful world", "url": "http://sourceforge.net/p/acolorfulworld/", "icon_url": "http://sourceforge.net/p/acolorfulworld/icon", "video_url": "", "screenshots": [{"url": "http://sourceforge.net/p/acolorfulworld/screenshot/Gameplay1.png", "caption": "Game play 1", "thumbnail_url": "http://sourceforge.net/p/acolorfulworld/screenshot/Gameplay1.png/thumb"}, {"url": "http://sourceforge.net/p/acolorfulworld/screenshot/Gameplay2.png", "caption": "Game play 2", "thumbnail_url": "http://sourceforge.net/p/acolorfulworld/screenshot/Gameplay2.png/thumb"}, {"url": "http://sourceforge.net/p/acolorfulworld/screenshot/MapEditor1.png", "caption": "Editor", "thumbnail_url": "http://sourceforge.net/p/acolorfulworld/screenshot/MapEditor1.png/thumb"}], "summary": "Sidescrolling game for Global Game Jam 2014", "short_description": "A puzzle platformer based on colors where hero can by-pass obstacles with different colors. Aim is to find a way to exit. We also developed an Arduino controller for game.", "moved_to_url": "", "shortname": "acolorfulworld", "developers": [{"url": "http://sourceforge.net/u/cemkalyoncu/", "username": "cemkalyoncu", "name": "Cem KALYONCU"}, {"url": "http://sourceforge.net/u/onurkoylu/", "username": "onurkoylu", "name": "onur"}, {"url": "http://sourceforge.net/u/cengizkandemir/", "username": "cengizkandemir", "name": "Cengiz Kandemir"}], "external_homepage": null}
