{"status": "active", "preferred_support_tool": "", "preferred_support_url": "", "labels": [], "private": false, "creation_date": "2008-04-14", "socialnetworks": [], "tools": [{"sourceforge_group_id": 224735, "mount_point": "summary", "name": "summary", "label": "Summary"}, {"mount_point": "support", "name": "support", "label": "Support"}, {"mount_point": "reviews", "name": "reviews", "label": "Reviews"}, {"mount_point": "files", "name": "files", "label": "Files"}, {"mount_point": "wiki", "name": "wiki", "label": "Wiki"}, {"mount_point": "mailman", "name": "mailman", "label": "Mailing Lists"}, {"mount_point": "code", "name": "svn", "label": "Code"}, {"mount_point": "activity", "name": "activity", "label": "Activity"}], "categories": {"developmentstatus": [{"fullpath": "Development Status :: 4 - Beta", "fullname": "4 - Beta", "shortname": "beta", "id": 10}], "environment": [{"fullpath": "User Interface :: Web-based", "fullname": "Web-based", "shortname": "web", "id": 237}], "language": [{"fullpath": "Programming Language :: Java", "fullname": "Java", "shortname": "java", "id": 198}], "license": [{"fullpath": "License :: OSI-Approved Open Source :: Apache License V2.0", "fullname": "Apache License V2.0", "shortname": "apache2", "id": 401}], "database": [{"fullpath": "Database Environment :: Database API :: JDBC", "fullname": "JDBC", "shortname": "db_api_jdbc", "id": 502}], "topic": [{"fullpath": "Topic :: Internet :: WWW/HTTP :: Dynamic Content :: CMS Systems", "fullname": "CMS Systems", "shortname": "cms", "id": 644}], "audience": [], "translation": [], "os": [{"fullpath": "Operating System :: Other Operating Systems :: Other", "fullname": "Other", "shortname": "other", "id": 212}]}, "_id": "517005af2718467b8b24c60a", "name": "BlueOxygen Aconix", "url": "http://sourceforge.net/p/aconix/", "icon_url": null, "video_url": "", "screenshots": [], "summary": "", "short_description": "BlueOxygen Aconix is a Content Management System that run on BlueOxygen Cimande.\r\n\r\nSeveral feature such as page collection, ordered collection, selected collection", "moved_to_url": "", "shortname": "aconix", "developers": [{"url": "http://sourceforge.net/u/userid-1367510/", "username": "pirate_153", "name": "Leo Haryanto"}, {"url": "http://sourceforge.net/u/fthamura/", "username": "fthamura", "name": "Frans Thamura - Meruvian"}, {"url": "http://sourceforge.net/u/kaskuers/", "username": "kaskuers", "name": "Bagus Candra L"}], "external_homepage": "http://www.blueoxygen.org"}
