{"status": "active", "preferred_support_tool": "", "preferred_support_url": "", "labels": [], "private": false, "creation_date": "2008-08-24", "socialnetworks": [], "tools": [{"mount_point": "support", "name": "support", "label": "Support"}, {"sourceforge_group_id": 237724, "mount_point": "summary", "name": "summary", "label": "Summary"}, {"mount_point": "reviews", "name": "reviews", "label": "Reviews"}, {"mount_point": "wiki", "name": "wiki", "label": "Wiki"}, {"mount_point": "files", "name": "files", "label": "Files"}, {"mount_point": "feature-requests", "name": "tickets", "label": "Feature Requests"}, {"mount_point": "code", "name": "svn", "label": "Code"}, {"mount_point": "activity", "name": "activity", "label": "Activity"}], "categories": {"developmentstatus": [{"fullpath": "Development Status :: 2 - Pre-Alpha", "fullname": "2 - Pre-Alpha", "shortname": "prealpha", "id": 8}], "environment": [{"fullpath": "User Interface :: Graphical :: OpenGL", "fullname": "OpenGL", "shortname": "ui_opengl", "id": 475}, {"fullpath": "User Interface :: Grouping and Descriptive Categories (UI) :: Project is a user interface (UI) system", "fullname": "Project is a user interface (UI) system", "shortname": "ui_meta_system", "id": 463}], "language": [{"fullpath": "Programming Language :: C++", "fullname": "C++", "shortname": "cpp", "id": 165}], "license": [{"fullpath": "License :: OSI-Approved Open Source :: MIT License", "fullname": "MIT License", "shortname": "mit", "id": 188}], "database": [], "topic": [{"fullpath": "Topic :: Games/Entertainment", "fullname": "Games/Entertainment", "shortname": "games", "id": 80}], "audience": [{"fullpath": "Intended Audience :: by End-User Class :: Developers", "fullname": "Developers", "shortname": "developers", "id": 3}], "translation": [{"fullpath": "Translations :: English", "fullname": "English", "shortname": "english", "id": 275}], "os": [{"fullpath": "Operating System :: Grouping and Descriptive Categories :: OS Portable (Source code to work with many OS platforms)", "fullname": "OS Portable (Source code to work with many OS platforms)", "shortname": "os_portable", "id": 436}]}, "_id": "517005b034309d2f53862f0b", "name": "AcrylicGUI", "url": "http://sourceforge.net/p/acrilyc/", "icon_url": null, "video_url": "", "screenshots": [], "summary": "", "short_description": "Free flexible and easy-to-use GUI library for OpenGL. Features: simple OO API; flexible widgets hierarhy; easy-to-customize XML-based visual styles; XML-based layout.", "moved_to_url": "", "shortname": "acrilyc", "developers": [{"url": "http://sourceforge.net/u/nofater/", "username": "nofater", "name": "Nofate"}], "external_homepage": "http://acrilyc.sourceforge.net"}
