{"status": "active", "preferred_support_tool": "", "preferred_support_url": "", "labels": [], "private": false, "creation_date": "2006-04-19", "socialnetworks": [], "tools": [{"sourceforge_group_id": 165888, "mount_point": "summary", "name": "summary", "label": "Summary"}, {"mount_point": "support", "name": "support", "label": "Support"}, {"mount_point": "reviews", "name": "reviews", "label": "Reviews"}, {"mount_point": "files", "name": "files", "label": "Files"}, {"mount_point": "wiki", "name": "wiki", "label": "Wiki"}, {"mount_point": "activity", "name": "activity", "label": "Activity"}], "categories": {"developmentstatus": [{"fullpath": "Development Status :: 2 - Pre-Alpha", "fullname": "2 - Pre-Alpha", "shortname": "prealpha", "id": 8}], "environment": [{"fullpath": "User Interface :: Web-based", "fullname": "Web-based", "shortname": "web", "id": 237}], "language": [{"fullpath": "Programming Language :: PHP", "fullname": "PHP", "shortname": "php", "id": 183}], "license": [{"fullpath": "License :: Public Domain", "fullname": "Public Domain", "shortname": "publicdomain", "id": 197}], "database": [{"fullpath": "Database Environment :: Network-based DBMS :: MySQL", "fullname": "MySQL", "shortname": "db_net_mysql", "id": 524}], "topic": [{"fullpath": "Topic :: Office/Business", "fullname": "Office/Business", "shortname": "office", "id": 129}, {"fullpath": "Topic :: Internet :: WWW/HTTP :: Dynamic Content", "fullname": "Dynamic Content", "shortname": "dynamic", "id": 92}], "audience": [{"fullpath": "Intended Audience :: by End-User Class :: System Administrators", "fullname": "System Administrators", "shortname": "sysadmins", "id": 4}], "translation": [{"fullpath": "Translations :: English", "fullname": "English", "shortname": "english", "id": 275}], "os": [{"fullpath": "Operating System :: Grouping and Descriptive Categories :: All POSIX (Linux/BSD/UNIX-like OSes)", "fullname": "All POSIX (Linux/BSD/UNIX-like OSes)", "shortname": "posix", "id": 200}]}, "_id": "516d843ae88f3d360a5c2b53", "name": "Acron", "url": "http://sourceforge.net/p/acron/", "icon_url": null, "video_url": "", "screenshots": [], "summary": "", "short_description": "PHP/MySQL based wiki application for acronyms. Anybody can add/edit acronyms that their organization uses.", "moved_to_url": "", "shortname": "acron", "developers": [{"url": "http://sourceforge.net/u/soichih/", "username": "soichih", "name": "Soichi Hayashi"}], "external_homepage": "http://acron.sourceforge.net"}
