{"status": "active", "preferred_support_tool": "_url", "preferred_support_url": "http://sourceforge.net/forum/forum.php?forum_id=421883", "labels": [], "private": false, "creation_date": "2004-11-10", "socialnetworks": [], "tools": [{"sourceforge_group_id": 123850, "mount_point": "summary", "name": "summary", "label": "Summary"}, {"mount_point": "support", "name": "support", "label": "Support"}, {"mount_point": "reviews", "name": "reviews", "label": "Reviews"}, {"mount_point": "files", "name": "files", "label": "Files"}, {"mount_point": "wiki", "name": "wiki", "label": "Wiki"}, {"mount_point": "bugs", "name": "tickets", "label": "Bugs"}, {"mount_point": "feature-requests", "name": "tickets", "label": "Feature Requests"}, {"mount_point": "discussion", "name": "discussion", "label": "Discussion"}, {"mount_point": "code", "name": "cvs", "label": "Code"}, {"mount_point": "activity", "name": "activity", "label": "Activity"}], "categories": {"developmentstatus": [], "environment": [], "language": [{"fullpath": "Programming Language :: Python", "fullname": "Python", "shortname": "python", "id": 178}], "license": [{"fullpath": "License :: OSI-Approved Open Source :: GNU General Public License version 2.0 (GPLv2)", "fullname": "GNU General Public License version 2.0 (GPLv2)", "shortname": "gpl", "id": 15}], "database": [], "topic": [{"fullpath": "Topic :: Office/Business", "fullname": "Office/Business", "shortname": "office", "id": 129}], "audience": [{"fullpath": "Intended Audience :: by End-User Class :: System Administrators", "fullname": "System Administrators", "shortname": "sysadmins", "id": 4}, {"fullpath": "Intended Audience :: by Industry or Sector :: Legal Industry", "fullname": "Legal Industry", "shortname": "legalindustry", "id": 364}], "translation": [], "os": [{"fullpath": "Operating System :: Modern (Vendor-Supported) Desktop Operating Systems :: Linux", "fullname": "Linux", "shortname": "linux", "id": 201}]}, "_id": "516c4e112718467af2b1c963", "name": "Acrophobia PDF Printer", "url": "http://sourceforge.net/p/acrophobia/", "icon_url": null, "video_url": "", "screenshots": [], "summary": "", "short_description": "Acrophobia is an easy to use network based PDF printer.  Acrophobia runs on Linux and is an excellent project for Linux newcomers.", "moved_to_url": "", "shortname": "acrophobia", "developers": [{"url": "http://sourceforge.net/u/jdaskew/", "username": "jdaskew", "name": "Jerry Askew"}, {"url": "http://sourceforge.net/u/skipbsmith/", "username": "skipbsmith", "name": "Skip Smith"}, {"url": "http://sourceforge.net/u/alavend/", "username": "alavend", "name": "alavend"}, {"url": "http://sourceforge.net/u/caldroun/", "username": "caldroun", "name": "Kreg Steppe"}], "external_homepage": "http://acrophobia.sourceforge.net"}
