{"status": "active", "preferred_support_tool": "", "preferred_support_url": "", "labels": [], "private": false, "creation_date": "2004-12-03", "socialnetworks": [], "tools": [{"sourceforge_group_id": 125711, "mount_point": "summary", "name": "summary", "label": "Summary"}, {"mount_point": "support", "name": "support", "label": "Support"}, {"mount_point": "reviews", "name": "reviews", "label": "Reviews"}, {"mount_point": "files", "name": "files", "label": "Files"}, {"mount_point": "wiki", "name": "wiki", "label": "Wiki"}, {"mount_point": "activity", "name": "activity", "label": "Activity"}], "categories": {"developmentstatus": [{"fullpath": "Development Status :: 2 - Pre-Alpha", "fullname": "2 - Pre-Alpha", "shortname": "prealpha", "id": 8}], "environment": [], "language": [{"fullpath": "Programming Language :: Perl", "fullname": "Perl", "shortname": "perl", "id": 176}], "license": [{"fullpath": "License :: Other License", "fullname": "Other License", "shortname": "other", "id": 196}], "database": [{"fullpath": "Database Environment :: Network-based DBMS :: MySQL", "fullname": "MySQL", "shortname": "db_net_mysql", "id": 524}], "topic": [{"fullpath": "Topic :: System :: Networking :: Monitoring", "fullname": "Monitoring", "shortname": "monitoring", "id": 152}], "audience": [{"fullpath": "Intended Audience :: by Industry or Sector :: Telecommunications Industry", "fullname": "Telecommunications Industry", "shortname": "telecommunications", "id": 368}, {"fullpath": "Intended Audience :: by End-User Class :: System Administrators", "fullname": "System Administrators", "shortname": "sysadmins", "id": 4}], "translation": [], "os": [{"fullpath": "Operating System :: Modern (Vendor-Supported) Desktop Operating Systems :: Linux", "fullname": "Linux", "shortname": "linux", "id": 201}, {"fullpath": "Operating System :: Modern (Vendor-Supported) Desktop Operating Systems :: FreeBSD", "fullname": "FreeBSD", "shortname": "freebsd", "id": 203}]}, "_id": "5159dd0727184634d574994e", "name": "ActiveMon", "url": "http://sourceforge.net/p/activemon/", "icon_url": null, "video_url": "", "screenshots": [], "summary": "", "short_description": "ActiveMon is a simple and extensible software framework for generation and analysis  of active network measurements that can be used for routine network health monitoring.", "moved_to_url": "", "shortname": "activemon", "developers": [{"url": "http://sourceforge.net/u/nhowes/", "username": "nhowes", "name": "Nathan Howes"}, {"url": "http://sourceforge.net/u/pcalyam/", "username": "pcalyam", "name": "Prasad Calyam"}, {"url": "http://sourceforge.net/u/pjaegersen/", "username": "pjaegersen", "name": "PJaegersen"}, {"url": "http://sourceforge.net/u/krymskiy/", "username": "krymskiy", "name": "krymskiy"}, {"url": "http://sourceforge.net/u/obahader/", "username": "obahader", "name": "Omar"}], "external_homepage": "http://activemon.sourceforge.net"}
