{"status": "active", "preferred_support_tool": "_url", "preferred_support_url": "http://sourceforge.net/forum/forum.php?forum_id=576073", "labels": [], "private": false, "creation_date": "2006-05-26", "socialnetworks": [], "tools": [{"mount_point": "code", "name": "svn", "label": "Code"}, {"sourceforge_group_id": 168719, "mount_point": "summary", "name": "summary", "label": "Summary"}, {"mount_point": "support", "name": "support", "label": "Support"}, {"mount_point": "reviews", "name": "reviews", "label": "Reviews"}, {"mount_point": "wiki", "name": "wiki", "label": "Wiki"}, {"mount_point": "files", "name": "files", "label": "Files"}, {"mount_point": "bugs", "name": "tickets", "label": "Bugs"}, {"mount_point": "news", "name": "blog", "label": "News"}, {"mount_point": "discussion", "name": "discussion", "label": "Discussion"}, {"mount_point": "mailman", "name": "mailman", "label": "Mailing Lists"}, {"mount_point": "activity", "name": "activity", "label": "Activity"}, {"mount_point": "link", "name": "link", "label": "Donate"}], "categories": {"developmentstatus": [{"fullpath": "Development Status :: 5 - Production/Stable", "fullname": "5 - Production/Stable", "shortname": "production", "id": 11}], "environment": [{"fullpath": "User Interface :: Non-interactive (Daemon)", "fullname": "Non-interactive (Daemon)", "shortname": "daemon", "id": 238}], "language": [{"fullpath": "Programming Language :: C++", "fullname": "C++", "shortname": "cpp", "id": 165}], "license": [{"fullpath": "License :: OSI-Approved Open Source :: Mozilla Public License 1.1 (MPL 1.1)", "fullname": "Mozilla Public License 1.1 (MPL 1.1)", "shortname": "mpl11", "id": 305}], "database": [], "topic": [{"fullpath": "Topic :: Communications :: Internet Phone", "fullname": "Internet Phone", "shortname": "internetphone", "id": 40}, {"fullpath": "Topic :: Communications :: Telephony", "fullname": "Telephony", "shortname": "telephony", "id": 247}, {"fullpath": "Topic :: Office/Business :: Enterprise", "fullname": "Enterprise", "shortname": "enterprise", "id": 576}], "audience": [{"fullpath": "Intended Audience :: by Industry or Sector :: Telecommunications Industry", "fullname": "Telecommunications Industry", "shortname": "telecommunications", "id": 368}, {"fullpath": "Intended Audience :: by End-User Class :: Advanced End Users", "fullname": "Advanced End Users", "shortname": "enduser_advanced", "id": 536}], "translation": [], "os": []}, "_id": "51a798f32718464edfa5eb2e", "name": "Activa for Asterisk", "url": "http://sourceforge.net/p/activa/", "icon_url": null, "video_url": "", "screenshots": [], "summary": "", "short_description": "Activa brings the Asterisk IP PBX to the call center. Built on top of Asterisk, Activa components enable successful call center implementations adding value in areas such as computer telephony, screenpop&click2dial, agent control, automatic dialing...", "moved_to_url": "", "shortname": "activa", "developers": [{"url": "http://sourceforge.net/u/qcondor/", "username": "qcondor", "name": "qcondor"}, {"url": "http://sourceforge.net/u/activa/", "username": "activa", "name": "activa"}, {"url": "http://sourceforge.net/u/activatsp/", "username": "activatsp", "name": "activatsp"}, {"url": "http://sourceforge.net/u/activa-team/", "username": "activa-team", "name": "Activa team developer"}], "external_homepage": "http://activa.sourceforge.net"}
